[
    {
        "run_ID": 1,
        "total_rew": 319.75,
        "run_time": 51.19
    },
    {
        "run_ID": 1,
        "total_rew": 177.34,
        "run_time": 41.35
    },
    {
        "run_ID": 1,
        "total_rew": 178.58,
        "run_time": 43.25
    },
    {
        "run_ID": 1,
        "total_rew": 177.32,
        "run_time": 43.25
    },
    {
        "run_ID": 1,
        "total_rew": 212.77,
        "run_time": 52.2
    },
    {
        "run_ID": 1,
        "total_rew": 177.22,
        "run_time": 44.0
    },
    {
        "run_ID": 1,
        "total_rew": 319.75,
        "run_time": 50.8
    },
    {
        "run_ID": 1,
        "total_rew": 208.1,
        "run_time": 52.2
    },
    {
        "run_ID": 1,
        "total_rew": 184.84,
        "run_time": 52.2
    },
    {
        "run_ID": 1,
        "total_rew": 218.69,
        "run_time": 52.2
    },
    {
        "run_ID": 1,
        "total_rew": 208.77,
        "run_time": 52.2
    },
    {
        "run_ID": 1,
        "total_rew": 319.68,
        "run_time": 51.15
    },
    {
        "run_ID": 1,
        "total_rew": 177.31,
        "run_time": 41.5
    },
    {
        "run_ID": 1,
        "total_rew": 319.65,
        "run_time": 47.85
    },
    {
        "run_ID": 1,
        "total_rew": 319.63,
        "run_time": 49.45
    },
    {
        "run_ID": 1,
        "total_rew": 178.7,
        "run_time": 41.6
    },
    {
        "run_ID": 1,
        "total_rew": 319.8,
        "run_time": 51.3
    },
    {
        "run_ID": 1,
        "total_rew": 217.85,
        "run_time": 52.2
    },
    {
        "run_ID": 1,
        "total_rew": 319.65,
        "run_time": 51.31
    },
    {
        "run_ID": 1,
        "total_rew": 205.59,
        "run_time": 52.45
    },
    {
        "run_ID": 1,
        "total_rew": 319.8,
        "run_time": 51.85
    },
    {
        "run_ID": 1,
        "total_rew": 177.49,
        "run_time": 42.15
    },
    {
        "run_ID": 1,
        "total_rew": 209.6,
        "run_time": 52.2
    },
    {
        "run_ID": 1,
        "total_rew": 219.37,
        "run_time": 52.2
    },
    {
        "run_ID": 1,
        "total_rew": 206.96,
        "run_time": 52.2
    },
    {
        "run_ID": 1,
        "total_rew": 319.72,
        "run_time": 48.45
    },
    {
        "run_ID": 1,
        "total_rew": 213.87,
        "run_time": 52.2
    },
    {
        "run_ID": 1,
        "total_rew": 319.63,
        "run_time": 50.65
    },
    {
        "run_ID": 1,
        "total_rew": 319.69,
        "run_time": 49.95
    },
    {
        "run_ID": 1,
        "total_rew": 87.51,
        "run_time": 25.0
    },
    {
        "run_ID": 1,
        "total_rew": 195.31,
        "run_time": 52.43
    },
    {
        "run_ID": 1,
        "total_rew": 319.82,
        "run_time": 50.8
    },
    {
        "run_ID": 1,
        "total_rew": 182.47,
        "run_time": 52.2
    },
    {
        "run_ID": 1,
        "total_rew": 185.13,
        "run_time": 52.2
    },
    {
        "run_ID": 1,
        "total_rew": 319.64,
        "run_time": 52.05
    }
]